CHANGES.txt
LICENSE.txt
MANIFEST.in
README.rst
requirements.txt
schema.txt
setup.py
bin/canvas_data_example.py
canvas_data/__init__.py
canvas_data/api.py
canvas_data/ddl_utils.py
canvas_data/exceptions.py
canvas_data/hmac_auth.py
canvas_data/scripts/__init__.py
canvas_data/scripts/canvasdata.py
canvas_data_3/__init__.py
canvas_data_3/api.py
canvas_data_3/ddl_utils.py
canvas_data_3/exceptions.py
canvas_data_3/hmac_auth.py
canvas_data_3/scripts/__init__.py
canvas_data_3/scripts/canvasdata.py
canvas_data_sdk.egg-info/PKG-INFO
canvas_data_sdk.egg-info/SOURCES.txt
canvas_data_sdk.egg-info/dependency_links.txt
canvas_data_sdk.egg-info/entry_points.txt
canvas_data_sdk.egg-info/requires.txt
canvas_data_sdk.egg-info/top_level.txt
docs/canvas_data.rst
docs/index.rst
docs/intro.rst