Metadata-Version: 1.0
Name: canvas-data-sdk
Version: 0.1.4
Summary: A Python SDK for working with Instructure's Canvas Data REST API.
Home-page: http://pypi.python.org/pypi/canvas-data-sdk/
Author: Colin Murtaugh
Author-email: cmurtaugh@gmail.com
License: LICENSE.txt
Platform: UNKNOWN
